{
  "title": "Zeitplan Stühlingen",
  "slug": "zeitplan-stuhlingen",
  "category": "project",
  "relativePath": "Projekte/z_Ergänzendes/Zeitplan/Zeitplan Stühlingen.md",
  "url": "notes/zeitplan-stuhlingen.html",
  "apiUrl": "api/notes/zeitplan-stuhlingen.json",
  "tags": [],
  "excerpt": "09.09. Untersuchung auf Haselmäuse (keine Maßnahmen) 11.09. Einreichen des Standsicherheitsnachweises Bis 26.09. Baufreigabe 01.10. Rodung der Südfläche, Entfernen der...",
  "frontmatter": {},
  "links": [],
  "markdown": "\n09.09.              Untersuchung auf Haselmäuse (keine Maßnahmen)\n\n11.09.              Einreichen des Standsicherheitsnachweises\n\nBis 26.09.        Baufreigabe\n\n01.10.              Rodung der Südfläche, Entfernen der Bauruine, Baufeldvorbereitung der Nord- und Südfläche\n\nNov-Feb          Bau auf der Nord- und Südfläche (Bauzeit je nach Witterung)"
}